act365/__init__.py
act365/booking.py
act365/cardholder.py
act365/cli.py
act365/client.py
act365-1.3.1.dist-info/METADATA
act365-1.3.1.dist-info/WHEEL
act365-1.3.1.dist-info/entry_points.txt
act365-1.3.1.dist-info/RECORD
