Metadata-Version: 2.3
Name: act365
Version: 1.3.1
Summary: Python Client for ACT365
Author: Simon McCartney
Author-email: simon@mccartney.ie
Requires-Python: >=3.11,<4.0
Classifier: Programming Language :: Python :: 3
Classifier: Programming Language :: Python :: 3.11
Classifier: Programming Language :: Python :: 3.12
Classifier: Programming Language :: Python :: 3.13
Requires-Dist: click (==8.1.8)
Requires-Dist: httpx (==0.27.0)
Requires-Dist: json5 (==0.9.25)
